repo_tools/VERSION
repo_tools/__init__.py
repo_tools/commands/circle.py
repo_tools/commands/config.py
repo_tools/commands/config_github.py
repo_tools/commands/config_projects.py
repo_tools/commands/github.py
repo_tools/commands/snippet.py
repo_tools/common/help_texts.py
repo_tools/common/structs.py
repo_tools/common/utils.py
repo_tools/main.py
repo_tools/snippets/info.sh
repo_tools-0.2.0.dist-info/entry_points.txt
repo_tools-0.2.0.dist-info/WHEEL
repo_tools-0.2.0.dist-info/METADATA
repo_tools-0.2.0.dist-info/RECORD
