Metadata-Version: 2.1
Name: repo-tools
Version: 0.2.0
Summary: A multi-repo CLI to help operating on multiple repos at the same time.
Author: Lightspeed Hospitality
Author-email: pt.hospitality.dev@lightspeedhq.com
Requires-Python: >=3.7,<4.0
Classifier: Programming Language :: Python :: 3
Classifier: Programming Language :: Python :: 3.7
Classifier: Programming Language :: Python :: 3.8
Classifier: Programming Language :: Python :: 3.9
Requires-Dist: GitPython (>=3.1,<4.0)
Requires-Dist: PyGithub (==1.53)
Requires-Dist: PyYAML (>=5.3,<6.0)
Requires-Dist: confuse (>=1.3,<2.0)
Requires-Dist: ruamel.yaml (>=0.16,<0.17)
Requires-Dist: tabulate (>=0.8,<0.9)
Requires-Dist: typer[all] (>=0.3,<0.4)
